{"agrupacion_ling\u00fc\u00edstica": "mixteco", "familia_ling\u00fc\u00edstica": "Oto-mangue", "autodenominaciones": [["tu\u2019un savi (de Ca\u00f1ada bajo)", "[t\u0169\u0294\u0169 sa\u03b2i]"]], "variante": "mixteco de Ca\u00f1ada bajo", "representaci\u00f3n_geogr\u00e1fica": [{"OAXACA": {"San Juan Bautista Cuicatl\u00e1n": ["Barrio de la Cruz, Barrio la Garita, Barrio Tecomavaca, Colonia la Cruz, El \u00c1guila Almoloyas, Estaci\u00f3n El Venado, Guadalupe de los Obos, Ojito de Agua, San Francisco Tutepetongo, San Gabriel Almoloyas, San Jos\u00e9 del Chilar, San Juan Bautista Cuicatl\u00e1n, San Juan Coyula, San Pablo Almoloyas, San Pedro Chicozapotes, San Pedro Nodon, Santa Cruz, Santa Mar\u00eda Almoloyas, Santiago Dominguillo (Alpichagua), Zapotillo"], "San Pedro Jaltepetongo": ["Guerrero, San Pedro Jaltepetongo, Veintiuno de Agosto"], "San Pedro Jocotipac": ["Cerro de la Cruz, Loma del Calvario, Rancho Buenavista, San Pedro Jocotipac"], "Santa Mar\u00eda Texcatitl\u00e1n": ["Barrio Llano Abajo, El Capisantu (Campo Santo), Jos\u00e9 Hern\u00e1ndez Z\u00e1rate, Palmar (El Rancho), Santa Mar\u00eda Texcatitl\u00e1n"], "Valerio Trujano": ["Rancho Ismael Aguirre Pe\u00f1a, Tomell\u00edn, Valerio Trujano"]}}]}