{"agrupacion_ling\u00fc\u00edstica": "otom\u00ed", "familia_ling\u00fc\u00edstica": "Oto-mangue", "autodenominaciones": ["\u00f1ath\u00f3/n[\u0272atho\u02e6]"], "variante": "<otom\u00ed del oeste>", "representaci\u00f3n_geogr\u00e1fica": [{"MICHOAC\u00c1N DE OCAMPO": {"Zit\u00e1cuaro": ["Agua Bendita (El Pocito), Agua Blanca (La Palma), Aputzio de Ju\u00e1rez (Santa Mar\u00eda), Camembaro, Carpinteros, Curunguro, Donaciano Ojeda (1ra. y 2da. Manzana San Francisco), El Bordo, El Derrumbadero, El Hortelano (Puerto de Santa Mar\u00eda), El Rinc\u00f3n de San Felipe (Hucaz 3ra. Manzana), El Tigre (2da. Manzana de Crescencio Morales), Francisco Serrato (San Bartolo), Heroica Zit\u00e1cuaro, La Capilla (3ra. Manzana de Francisco Serrato), La Carne Hedionda, La Cumbre (5ta. Manzana de Crescencio Morales), La Mesa, La Mesa del Rinc\u00f3n de Curungueo, La Presa (2da. Manzana Barrio de Santa Cruz), La Viguita (4ta. Manzana de Crescencio Morales), Linda Vista (El Bosque 4ta. Manzana de Aputzio), Los Polvillos (Crucero 4ta. Manzana Zirahuato), Macutzio, Mesa de Loma Larga (Loma Bonita), Mesa de los Alzati (2da. Mza de San Felipe), Mesas de Enandio (Cuarta Manzana), Ocurio, Ojo de Agua de San Felipe (1ra. Manzana), Puerto de San Felipe (Rancho el Tr\u00e9bol), Rinc\u00f3n de Curungueo (2da. Manzana de Curungueo), Rinc\u00f3n de Nicol\u00e1s Romero (Cedros 3ra. Manzana), Rinc\u00f3n del Ahorcado, R\u00edo de Guadalupe (4ta. Manzana Crescencio Morales), San Felipe los Alzati (Colonia Nueva), San Francisco Curungueo (Curungueo), Tercera Manzana de Crescencio Morales (Capul\u00edn), Valle Verde (Primera Manzana de Curungueo), Zirahuato de los Bernal [Zirahuato]."]}}]}